depfinder/__init__.py
depfinder/_version.py
depfinder/cli.py
depfinder/inspection.py
depfinder/main.py
depfinder/reports.py
depfinder/stdliblist.py
depfinder/utils.py
depfinder/pkg_data/name_mapping.yml
depfinder/pkg_data/pkg_data.yml
depfinder-2.10.0.dist-info/LICENSE
depfinder-2.10.0.dist-info/METADATA
depfinder-2.10.0.dist-info/WHEEL
depfinder-2.10.0.dist-info/entry_points.txt
depfinder-2.10.0.dist-info/top_level.txt
depfinder-2.10.0.dist-info/zip-safe
depfinder-2.10.0.dist-info/RECORD
