Metadata-Version: 2.1
Name: depfinder
Version: 2.10.0
Summary: Find all the imports in your library
Home-page: http://github.com/ericdill/depfinder
Author: Eric Dill
Author-email: thedizzle@gmail.com
License: BSD-3-Clause
Project-URL: Documentation, https://ericdill.github.io/depfinder
Project-URL: Bug Tracker, https://github.com/ericdill/depfinder/issues
Project-URL: Source Code, https://github.com/ericdill/depfinder
Requires-Python: >=2.7
License-File: LICENSE
Requires-Dist: pyyaml
Requires-Dist: requests
Requires-Dist: stdlib-list ; python_version < "3.10"
Provides-Extra: conda-forge
Requires-Dist: conda-forge-metadata (>=0.3.0) ; extra == 'conda-forge'
